copick_shared_ui/__init__.py
copick_shared_ui/core/__init__.py
copick_shared_ui/core/image_interface.py
copick_shared_ui/core/models.py
copick_shared_ui/core/thumbnail_cache.py
copick_shared_ui/platform/__init__.py
copick_shared_ui/platform/chimerax_integration.py
copick_shared_ui/platform/napari_integration.py
copick_shared_ui/theming/__init__.py
copick_shared_ui/theming/colors.py
copick_shared_ui/theming/styles.py
copick_shared_ui/theming/theme_detection.py
copick_shared_ui/ui/__init__.py
copick_shared_ui/ui/edit_object_types_dialog.py
copick_shared_ui/util/__init__.py
copick_shared_ui/util/validation.py
copick_shared_ui/widgets/__init__.py
copick_shared_ui/widgets/gallery/__init__.py
copick_shared_ui/widgets/gallery/gallery_widget.py
copick_shared_ui/widgets/gallery/run_card.py
copick_shared_ui/widgets/info/__init__.py
copick_shared_ui/widgets/info/info_widget.py
copick_shared_ui/workers/__init__.py
copick_shared_ui/workers/base.py
copick_shared_ui/workers/base_manager.py
copick_shared_ui/workers/chimerax.py
copick_shared_ui/workers/data_worker.py
copick_shared_ui/workers/napari.py
copick_shared_ui/workers/unified_workers.py
copick_shared_ui-0.2.0.dist-info/METADATA
copick_shared_ui-0.2.0.dist-info/WHEEL
copick_shared_ui-0.2.0.dist-info/licenses/LICENSE
copick_shared_ui-0.2.0.dist-info/RECORD
