Metadata-Version: 2.4
Name: copick-shared-ui
Version: 0.2.0
Summary: Shared UI components for copick visualization plugins
Project-URL: Repository, https://github.com/copick/copick-shared-ui
Project-URL: Issues, https://github.com/copick/copick-shared-ui/issues
Project-URL: Documentation, https://github.com/copick/copick-shared-ui#README.md
Project-URL: Bug Tracker, https://github.com/copick/copick-shared-ui/issues
Project-URL: Source Code, https://github.com/copick/copick-shared-ui
Project-URL: User Support, https://github.com/copick/copick-shared-ui/issues
Author-email: "Utz H. Ermel" <utz@ermel.me>, Kyle Harrington <czi@kyleharrington.com>
License: MIT License
License-File: LICENSE
Keywords: annotation,copick,cryo-et,cryoet,qt,tomography,ui
Classifier: Development Status :: 2 - Pre-Alpha
Classifier: Intended Audience :: Developers
Classifier: License :: OSI Approved :: MIT License
Classifier: Operating System :: OS Independent
Classifier: Programming Language :: Python
Classifier: Programming Language :: Python :: 3
Classifier: Programming Language :: Python :: 3 :: Only
Classifier: Programming Language :: Python :: 3.9
Classifier: Programming Language :: Python :: 3.10
Classifier: Programming Language :: Python :: 3.11
Classifier: Programming Language :: Python :: 3.12
Classifier: Programming Language :: Python :: 3.13
Classifier: Programming Language :: Python :: Implementation :: CPython
Classifier: Programming Language :: Python :: Implementation :: PyPy
Classifier: Topic :: Scientific/Engineering :: Image Processing
Requires-Python: >=3.9
Requires-Dist: copick[all]>=1.5.0
Requires-Dist: numpy>=1.21.0
Requires-Dist: pydantic>=2
Requires-Dist: qtpy
Requires-Dist: superqt
Requires-Dist: zarr<3
Provides-Extra: dev
Requires-Dist: black>=25.1.0; extra == 'dev'
Requires-Dist: hatch-vcs>=0.4.0; extra == 'dev'
Requires-Dist: hatchling>=1.25.0; extra == 'dev'
Requires-Dist: pre-commit>=4.2.0; extra == 'dev'
Requires-Dist: ruff>=0.12.0; extra == 'dev'
Provides-Extra: testing
Requires-Dist: pyqt6; extra == 'testing'
Requires-Dist: pytest; extra == 'testing'
Requires-Dist: pytest-cov; extra == 'testing'
Requires-Dist: pytest-qt; extra == 'testing'
Requires-Dist: tox; extra == 'testing'
Requires-Dist: tox-gh-actions; extra == 'testing'
Requires-Dist: tox-uv; extra == 'testing'
